pactester/__init__.py
pactester/config.py
pactester/main.py
pactester-1.0.1.dist-info/LICENSE
pactester-1.0.1.dist-info/METADATA
pactester-1.0.1.dist-info/WHEEL
pactester-1.0.1.dist-info/entry_points.txt
pactester-1.0.1.dist-info/RECORD
