Metadata-Version: 2.3
Name: pactester
Version: 1.0.1
Summary: Command-line tool to check proxy resolution using PAC files
License: GPL-3.0
Author: Javier Correa Guerrero
Author-email: jcorreag@pm.me
Requires-Python: >=3.9,<3.13
Classifier: License :: OSI Approved :: GNU General Public License v3 (GPLv3)
Classifier: Programming Language :: Python :: 3
Classifier: Programming Language :: Python :: 3.9
Classifier: Programming Language :: Python :: 3.10
Classifier: Programming Language :: Python :: 3.11
Classifier: Programming Language :: Python :: 3.12
Requires-Dist: pacparser (>=1.3.7)
Requires-Dist: platformdirs (>=4.00)
Requires-Dist: requests (>=2.25.0)
Requires-Dist: toml (>=0.10.2)
